[
    {
        "id": 1,
        "name": "Uso de la aplicación",
        "icon": "book",
        "tags": [
            {"id": 1, "name": "Uso general"},
            {"id": 2, "name": "Aspectos"}
        ]
    }, 
    {
        "id": 2,
        "name": "Conexión entre módulo ESP32 y Firebase DB",
        "icon": "database",
        "tags": [
            {"id": 1, "name": "Explicación"}
        ]
    },
    {
        "id": 3,
        "name": "Conexión física entre módulo ESP32 y sensor DHT22",
        "icon": "microchip",
        "tags": [
            {"id": 1, "name": "Código"},
            {"id": 2, "name": "Esquema"}
        ]
    },
    {
        "id": 4,
        "name": "Conexión física entre módulo ESP32 y sensor MQ135",
        "icon": "wind",
        "tags": [
            {"id": 1, "name": "Código"},
            {"id": 2, "name": "Esquema"}
        ]
    },
    {
        "id": 5,
        "name": "Funcionamiento del sistema de riego y sensor de humedad de suelo",
        "icon": "tint",
        "tags": [
            {"id": 1, "name": "Código"},
            {"id": 2, "name": "Esquema"}
        ]
    }
]