[
  {
    "name": "Temperatura",
    "variables": [
      {
        "name": "Setpoint Temperatura (°C)",
        "value": "temperature_sp", 
        "predefined": "33"
      },
      {
        "name": "Constante Proporcional (KP)",
        "value": "kp",
        "predefined": "740"
      },
      {
        "name": "Constante Integral (KI)",
        "value": "ki",
        "predefined": "17.2"
      },
      {
        "name": "Constante Derivativa (KD)",
        "value": "kd",
        "predefined": "5.6"
      }
    ]
  },
  {
    "name": "Humedad de suelo",
    "variables": [
      {
        "name": "Activación de bomba de agua [%]",
        "value": "ground_humidity_sp",
        "predefined": "30"
      }
    ]
  },
  {
    "name": "Sistema de riego",
    "variables": [
      {
        "name": "Desactivación de bomba de agua [%]",
        "value": "irrigation_sp",
        "predefined": "20"
      }
    ]
  }

]